{
  "$type": "Comindware.Platform.Contracts.FormModel, Comindware.Platform.Contracts",
  "GlobalAlias": {
    "$type": "Comindware.Platform.Contracts.GlobalAlias, Comindware.Platform.Contracts",
    "Type": "Form",
    "Owner": "Ezhednevnayazayavka",
    "Alias": "defaultForm"
  },
  "Type": "PublicForm",
  "IsDefault": true,
  "Root": {
    "$type": "Comindware.Platform.Contracts.VerticalLayoutModel, Comindware.Platform.Contracts",
    "Rows": {
      "$type": "System.Collections.Generic.List`1[[Comindware.Platform.Contracts.FormComponentModel, Comindware.Platform.Contracts]], mscorlib",
      "$values": [
        {
          "$type": "Comindware.Platform.Contracts.PanelModel, Comindware.Platform.Contracts",
          "Text": {
            "$type": "Comindware.Platform.Contracts.LocalizedTextModel, Comindware.Platform.Contracts",
            "En": "Новая область",
            "De": "Новая область",
            "Ru": "Новая область"
          },
          "OriginalType": "GroupPanel",
          "Rows": {
            "$type": "System.Collections.Generic.List`1[[Comindware.Platform.Contracts.FormComponentModel, Comindware.Platform.Contracts]], mscorlib",
            "$values": [
              {
                "$type": "Comindware.Platform.Contracts.VerticalLayoutModel, Comindware.Platform.Contracts",
                "Rows": {
                  "$type": "System.Collections.Generic.List`1[[Comindware.Platform.Contracts.FormComponentModel, Comindware.Platform.Contracts]], mscorlib",
                  "$values": [
                    {
                      "$type": "Comindware.Platform.Contracts.LayoutModel, Comindware.Platform.Contracts",
                      "Components": {
                        "$type": "System.Collections.Generic.List`1[[Comindware.Platform.Contracts.FormComponentModel, Comindware.Platform.Contracts]], mscorlib",
                        "$values": [
                          {
                            "$type": "Comindware.Platform.Contracts.VerticalLayoutModel, Comindware.Platform.Contracts",
                            "Rows": {
                              "$type": "System.Collections.Generic.List`1[[Comindware.Platform.Contracts.FormComponentModel, Comindware.Platform.Contracts]], mscorlib",
                              "$values": [
                                {
                                  "$type": "Comindware.Platform.Contracts.FieldComponentModel, Comindware.Platform.Contracts",
                                  "Label": {
                                    "$type": "Comindware.Platform.Contracts.LabelModel, Comindware.Platform.Contracts",
                                    "Hidden": false,
                                    "Alignment": "Top",
                                    "Text": {
                                      "$type": "Comindware.Platform.Contracts.LocalizedTextModel, Comindware.Platform.Contracts",
                                      "En": "Проект для заявки",
                                      "De": "Проект для заявки",
                                      "Ru": "Проект для заявки"
                                    }
                                  },
                                  "FieldType": "Reference",
                                  "Placeholder": {
                                    "$type": "Comindware.Platform.Contracts.LocalizedTextModel, Comindware.Platform.Contracts"
                                  },
                                  "HelpText": {
                                    "$type": "Comindware.Platform.Contracts.LocalizedTextModel, Comindware.Platform.Contracts"
                                  },
                                  "PropertyPath": {
                                    "$type": "Comindware.Platform.Contracts.GlobalAlias[], Comindware.Platform.Contracts",
                                    "$values": [
                                      {
                                        "$type": "Comindware.Platform.Contracts.GlobalAlias, Comindware.Platform.Contracts",
                                        "Type": "Attribute",
                                        "Owner": "Ezhednevnayazayavka",
                                        "Alias": "Proektdlyazayavki"
                                      }
                                    ]
                                  },
                                  "EditorType": "Radio",
                                  "CreationType": "None",
                                  "RemovalType": "None",
                                  "EditType": "None",
                                  "HideSearchBar": false,
                                  "ShowAsLink": false,
                                  "ChildPropertyAlias": {
                                    "$type": "Comindware.Platform.Contracts.GlobalAlias, Comindware.Platform.Contracts",
                                    "Type": "Undefined"
                                  },
                                  "OrderPropertyAlias": {
                                    "$type": "Comindware.Platform.Contracts.GlobalAlias, Comindware.Platform.Contracts",
                                    "Type": "Undefined"
                                  },
                                  "NumberPropertyAlias": {
                                    "$type": "Comindware.Platform.Contracts.GlobalAlias, Comindware.Platform.Contracts",
                                    "Type": "Undefined"
                                  },
                                  "PrecedentPropertyAlias": {
                                    "$type": "Comindware.Platform.Contracts.GlobalAlias, Comindware.Platform.Contracts",
                                    "Type": "Undefined"
                                  },
                                  "SortingDirection": "Asc",
                                  "PopupFormAlias": {
                                    "$type": "Comindware.Platform.Contracts.GlobalAlias, Comindware.Platform.Contracts",
                                    "Type": "Undefined"
                                  },
                                  "AllowEdit": false,
                                  "DisplayFormat": "ShowAsPicture",
                                  "GlobalAlias": {
                                    "$type": "Comindware.Platform.Contracts.GlobalAlias, Comindware.Platform.Contracts",
                                    "Type": "FormComponent",
                                    "Alias": "Proektdlyazayavki"
                                  },
                                  "AccessType": "Editable",
                                  "Width": 0,
                                  "Type": "FieldComponent"
                                },
                                {
                                  "$type": "Comindware.Platform.Contracts.FieldComponentModel, Comindware.Platform.Contracts",
                                  "Label": {
                                    "$type": "Comindware.Platform.Contracts.LabelModel, Comindware.Platform.Contracts",
                                    "Hidden": false,
                                    "Alignment": "Top",
                                    "Text": {
                                      "$type": "Comindware.Platform.Contracts.LocalizedTextModel, Comindware.Platform.Contracts",
                                      "En": "Дата исполнения",
                                      "De": "Дата исполнения",
                                      "Ru": "Дата исполнения"
                                    }
                                  },
                                  "FieldType": "Date",
                                  "Placeholder": {
                                    "$type": "Comindware.Platform.Contracts.LocalizedTextModel, Comindware.Platform.Contracts"
                                  },
                                  "HelpText": {
                                    "$type": "Comindware.Platform.Contracts.LocalizedTextModel, Comindware.Platform.Contracts"
                                  },
                                  "PropertyPath": {
                                    "$type": "Comindware.Platform.Contracts.GlobalAlias[], Comindware.Platform.Contracts",
                                    "$values": [
                                      {
                                        "$type": "Comindware.Platform.Contracts.GlobalAlias, Comindware.Platform.Contracts",
                                        "Type": "Attribute",
                                        "Owner": "Ezhednevnayazayavka",
                                        "Alias": "Dataispolneniya"
                                      }
                                    ]
                                  },
                                  "EditorType": "Radio",
                                  "CreationType": "None",
                                  "RemovalType": "None",
                                  "EditType": "None",
                                  "DisplayTime": false,
                                  "ChildPropertyAlias": {
                                    "$type": "Comindware.Platform.Contracts.GlobalAlias, Comindware.Platform.Contracts",
                                    "Type": "Undefined"
                                  },
                                  "OrderPropertyAlias": {
                                    "$type": "Comindware.Platform.Contracts.GlobalAlias, Comindware.Platform.Contracts",
                                    "Type": "Undefined"
                                  },
                                  "NumberPropertyAlias": {
                                    "$type": "Comindware.Platform.Contracts.GlobalAlias, Comindware.Platform.Contracts",
                                    "Type": "Undefined"
                                  },
                                  "PrecedentPropertyAlias": {
                                    "$type": "Comindware.Platform.Contracts.GlobalAlias, Comindware.Platform.Contracts",
                                    "Type": "Undefined"
                                  },
                                  "SortingDirection": "Asc",
                                  "PopupFormAlias": {
                                    "$type": "Comindware.Platform.Contracts.GlobalAlias, Comindware.Platform.Contracts",
                                    "Type": "Undefined"
                                  },
                                  "DisplayFormat": "ShowAsPicture",
                                  "GlobalAlias": {
                                    "$type": "Comindware.Platform.Contracts.GlobalAlias, Comindware.Platform.Contracts",
                                    "Type": "FormComponent",
                                    "Alias": "Dataispolneniya"
                                  },
                                  "AccessType": "Editable",
                                  "Width": 0,
                                  "Type": "FieldComponent"
                                }
                              ]
                            },
                            "GlobalAlias": {
                              "$type": "Comindware.Platform.Contracts.GlobalAlias, Comindware.Platform.Contracts",
                              "Type": "FormComponent",
                              "Alias": "VerticalLayout2"
                            },
                            "AccessType": "Undefined",
                            "Width": 50,
                            "Type": "VerticalLayout"
                          },
                          {
                            "$type": "Comindware.Platform.Contracts.VerticalLayoutModel, Comindware.Platform.Contracts",
                            "Rows": {
                              "$type": "System.Collections.Generic.List`1[[Comindware.Platform.Contracts.FormComponentModel, Comindware.Platform.Contracts]], mscorlib",
                              "$values": [
                                {
                                  "$type": "Comindware.Platform.Contracts.FieldComponentModel, Comindware.Platform.Contracts",
                                  "Label": {
                                    "$type": "Comindware.Platform.Contracts.LabelModel, Comindware.Platform.Contracts",
                                    "Hidden": false,
                                    "Alignment": "Top",
                                    "Text": {
                                      "$type": "Comindware.Platform.Contracts.LocalizedTextModel, Comindware.Platform.Contracts",
                                      "En": "К исполнению",
                                      "De": "К исполнению",
                                      "Ru": "К исполнению"
                                    }
                                  },
                                  "FieldType": "Boolean",
                                  "Placeholder": {
                                    "$type": "Comindware.Platform.Contracts.LocalizedTextModel, Comindware.Platform.Contracts"
                                  },
                                  "HelpText": {
                                    "$type": "Comindware.Platform.Contracts.LocalizedTextModel, Comindware.Platform.Contracts"
                                  },
                                  "PropertyPath": {
                                    "$type": "Comindware.Platform.Contracts.GlobalAlias[], Comindware.Platform.Contracts",
                                    "$values": [
                                      {
                                        "$type": "Comindware.Platform.Contracts.GlobalAlias, Comindware.Platform.Contracts",
                                        "Type": "Attribute",
                                        "Owner": "Ezhednevnayazayavka",
                                        "Alias": "Kispolneniyu"
                                      }
                                    ]
                                  },
                                  "TrueText": {
                                    "$type": "Comindware.Platform.Contracts.LocalizedTextModel, Comindware.Platform.Contracts"
                                  },
                                  "FalseText": {
                                    "$type": "Comindware.Platform.Contracts.LocalizedTextModel, Comindware.Platform.Contracts"
                                  },
                                  "UseTrueFalseText": false,
                                  "EditorType": "Checkbox",
                                  "CreationType": "None",
                                  "RemovalType": "None",
                                  "EditType": "None",
                                  "ChildPropertyAlias": {
                                    "$type": "Comindware.Platform.Contracts.GlobalAlias, Comindware.Platform.Contracts",
                                    "Type": "Undefined"
                                  },
                                  "OrderPropertyAlias": {
                                    "$type": "Comindware.Platform.Contracts.GlobalAlias, Comindware.Platform.Contracts",
                                    "Type": "Undefined"
                                  },
                                  "NumberPropertyAlias": {
                                    "$type": "Comindware.Platform.Contracts.GlobalAlias, Comindware.Platform.Contracts",
                                    "Type": "Undefined"
                                  },
                                  "PrecedentPropertyAlias": {
                                    "$type": "Comindware.Platform.Contracts.GlobalAlias, Comindware.Platform.Contracts",
                                    "Type": "Undefined"
                                  },
                                  "SortingDirection": "Asc",
                                  "PopupFormAlias": {
                                    "$type": "Comindware.Platform.Contracts.GlobalAlias, Comindware.Platform.Contracts",
                                    "Type": "Undefined"
                                  },
                                  "DisplayFormat": "ShowAsPicture",
                                  "GlobalAlias": {
                                    "$type": "Comindware.Platform.Contracts.GlobalAlias, Comindware.Platform.Contracts",
                                    "Type": "FormComponent",
                                    "Alias": "Kispolneniyu"
                                  },
                                  "AccessType": "Editable",
                                  "Width": 0,
                                  "Type": "FieldComponent"
                                }
                              ]
                            },
                            "GlobalAlias": {
                              "$type": "Comindware.Platform.Contracts.GlobalAlias, Comindware.Platform.Contracts",
                              "Type": "FormComponent",
                              "Alias": "VerticalLayout3"
                            },
                            "AccessType": "Undefined",
                            "Width": 50,
                            "Type": "VerticalLayout"
                          }
                        ]
                      },
                      "OriginalType": "HorizontalLayout",
                      "GlobalAlias": {
                        "$type": "Comindware.Platform.Contracts.GlobalAlias, Comindware.Platform.Contracts",
                        "Type": "FormComponent",
                        "Alias": "HorizontalLayout"
                      },
                      "AccessType": "Undefined",
                      "Width": 0,
                      "Type": "LayoutModel"
                    },
                    {
                      "$type": "Comindware.Platform.Contracts.FieldComponentModel, Comindware.Platform.Contracts",
                      "Label": {
                        "$type": "Comindware.Platform.Contracts.LabelModel, Comindware.Platform.Contracts",
                        "Hidden": false,
                        "Alignment": "Top",
                        "Text": {
                          "$type": "Comindware.Platform.Contracts.LocalizedTextModel, Comindware.Platform.Contracts",
                          "En": "Строки заявки",
                          "De": "Строки заявки",
                          "Ru": "Строки заявки"
                        }
                      },
                      "FieldType": "Table",
                      "Placeholder": {
                        "$type": "Comindware.Platform.Contracts.LocalizedTextModel, Comindware.Platform.Contracts"
                      },
                      "HelpText": {
                        "$type": "Comindware.Platform.Contracts.LocalizedTextModel, Comindware.Platform.Contracts"
                      },
                      "PropertyPath": {
                        "$type": "Comindware.Platform.Contracts.GlobalAlias[], Comindware.Platform.Contracts",
                        "$values": [
                          {
                            "$type": "Comindware.Platform.Contracts.GlobalAlias, Comindware.Platform.Contracts",
                            "Type": "Attribute",
                            "Owner": "Ezhednevnayazayavka",
                            "Alias": "Khotelki"
                          }
                        ]
                      },
                      "EditorType": "Radio",
                      "CreationType": "None",
                      "RemovalType": "None",
                      "EditType": "None",
                      "Columns": {
                        "$type": "System.Collections.Generic.List`1[[Comindware.Platform.Contracts.FieldComponentModel, Comindware.Platform.Contracts]], mscorlib",
                        "$values": [
                          {
                            "$type": "Comindware.Platform.Contracts.FieldComponentModel, Comindware.Platform.Contracts",
                            "Label": {
                              "$type": "Comindware.Platform.Contracts.LabelModel, Comindware.Platform.Contracts",
                              "Hidden": false,
                              "Alignment": "Undefined",
                              "Text": {
                                "$type": "Comindware.Platform.Contracts.LocalizedTextModel, Comindware.Platform.Contracts",
                                "En": "Хотелка",
                                "De": "Хотелка",
                                "Ru": "Хотелка"
                              }
                            },
                            "FieldType": "TableColumn",
                            "Placeholder": {
                              "$type": "Comindware.Platform.Contracts.LocalizedTextModel, Comindware.Platform.Contracts"
                            },
                            "HelpText": {
                              "$type": "Comindware.Platform.Contracts.LocalizedTextModel, Comindware.Platform.Contracts"
                            },
                            "PropertyPath": {
                              "$type": "Comindware.Platform.Contracts.GlobalAlias[], Comindware.Platform.Contracts",
                              "$values": [
                                {
                                  "$type": "Comindware.Platform.Contracts.GlobalAlias, Comindware.Platform.Contracts",
                                  "Type": "Attribute",
                                  "Owner": "Strokiezhednevnoyzayavki",
                                  "Alias": "Khotelka"
                                }
                              ]
                            },
                            "EditorType": "Radio",
                            "CreationType": "None",
                            "RemovalType": "None",
                            "EditType": "None",
                            "ChildPropertyAlias": {
                              "$type": "Comindware.Platform.Contracts.GlobalAlias, Comindware.Platform.Contracts",
                              "Type": "Undefined"
                            },
                            "OrderPropertyAlias": {
                              "$type": "Comindware.Platform.Contracts.GlobalAlias, Comindware.Platform.Contracts",
                              "Type": "Undefined"
                            },
                            "NumberPropertyAlias": {
                              "$type": "Comindware.Platform.Contracts.GlobalAlias, Comindware.Platform.Contracts",
                              "Type": "Undefined"
                            },
                            "PrecedentPropertyAlias": {
                              "$type": "Comindware.Platform.Contracts.GlobalAlias, Comindware.Platform.Contracts",
                              "Type": "Undefined"
                            },
                            "SortingDirection": "Asc",
                            "PopupFormAlias": {
                              "$type": "Comindware.Platform.Contracts.GlobalAlias, Comindware.Platform.Contracts",
                              "Type": "Undefined"
                            },
                            "AllowEdit": false,
                            "DisplayFormat": "ShowAsPicture",
                            "GlobalAlias": {
                              "$type": "Comindware.Platform.Contracts.GlobalAlias, Comindware.Platform.Contracts",
                              "Type": "FormComponent",
                              "Alias": "Khotelki3_Khotelka"
                            },
                            "AccessType": "Editable",
                            "Width": 480,
                            "Type": "FieldComponent"
                          },
                          {
                            "$type": "Comindware.Platform.Contracts.FieldComponentModel, Comindware.Platform.Contracts",
                            "Label": {
                              "$type": "Comindware.Platform.Contracts.LabelModel, Comindware.Platform.Contracts",
                              "Hidden": false,
                              "Alignment": "Undefined",
                              "Text": {
                                "$type": "Comindware.Platform.Contracts.LocalizedTextModel, Comindware.Platform.Contracts",
                                "En": "Количество заказа",
                                "De": "Количество заказа",
                                "Ru": "Количество заказа"
                              }
                            },
                            "FieldType": "TableColumn",
                            "Placeholder": {
                              "$type": "Comindware.Platform.Contracts.LocalizedTextModel, Comindware.Platform.Contracts"
                            },
                            "HelpText": {
                              "$type": "Comindware.Platform.Contracts.LocalizedTextModel, Comindware.Platform.Contracts"
                            },
                            "PropertyPath": {
                              "$type": "Comindware.Platform.Contracts.GlobalAlias[], Comindware.Platform.Contracts",
                              "$values": [
                                {
                                  "$type": "Comindware.Platform.Contracts.GlobalAlias, Comindware.Platform.Contracts",
                                  "Type": "Attribute",
                                  "Owner": "Strokiezhednevnoyzayavki",
                                  "Alias": "Kolichestvozakaza"
                                }
                              ]
                            },
                            "EditorType": "Radio",
                            "CreationType": "None",
                            "RemovalType": "None",
                            "EditType": "None",
                            "ChildPropertyAlias": {
                              "$type": "Comindware.Platform.Contracts.GlobalAlias, Comindware.Platform.Contracts",
                              "Type": "Undefined"
                            },
                            "OrderPropertyAlias": {
                              "$type": "Comindware.Platform.Contracts.GlobalAlias, Comindware.Platform.Contracts",
                              "Type": "Undefined"
                            },
                            "NumberPropertyAlias": {
                              "$type": "Comindware.Platform.Contracts.GlobalAlias, Comindware.Platform.Contracts",
                              "Type": "Undefined"
                            },
                            "PrecedentPropertyAlias": {
                              "$type": "Comindware.Platform.Contracts.GlobalAlias, Comindware.Platform.Contracts",
                              "Type": "Undefined"
                            },
                            "SortingDirection": "Asc",
                            "PopupFormAlias": {
                              "$type": "Comindware.Platform.Contracts.GlobalAlias, Comindware.Platform.Contracts",
                              "Type": "Undefined"
                            },
                            "AllowEdit": false,
                            "DisplayFormat": "ShowAsPicture",
                            "GlobalAlias": {
                              "$type": "Comindware.Platform.Contracts.GlobalAlias, Comindware.Platform.Contracts",
                              "Type": "FormComponent",
                              "Alias": "Khotelki3_Kolichestvozakaza"
                            },
                            "AccessType": "Editable",
                            "Width": 120,
                            "Type": "FieldComponent"
                          },
                          {
                            "$type": "Comindware.Platform.Contracts.FieldComponentModel, Comindware.Platform.Contracts",
                            "Label": {
                              "$type": "Comindware.Platform.Contracts.LabelModel, Comindware.Platform.Contracts",
                              "Hidden": false,
                              "Alignment": "Undefined",
                              "Text": {
                                "$type": "Comindware.Platform.Contracts.LocalizedTextModel, Comindware.Platform.Contracts",
                                "En": "ЕИ",
                                "De": "ЕИ",
                                "Ru": "ЕИ"
                              }
                            },
                            "FieldType": "TableColumn",
                            "Placeholder": {
                              "$type": "Comindware.Platform.Contracts.LocalizedTextModel, Comindware.Platform.Contracts"
                            },
                            "HelpText": {
                              "$type": "Comindware.Platform.Contracts.LocalizedTextModel, Comindware.Platform.Contracts"
                            },
                            "PropertyPath": {
                              "$type": "Comindware.Platform.Contracts.GlobalAlias[], Comindware.Platform.Contracts",
                              "$values": [
                                {
                                  "$type": "Comindware.Platform.Contracts.GlobalAlias, Comindware.Platform.Contracts",
                                  "Type": "Attribute",
                                  "Owner": "Strokiezhednevnoyzayavki",
                                  "Alias": "EI"
                                }
                              ]
                            },
                            "EditorType": "Radio",
                            "CreationType": "None",
                            "RemovalType": "None",
                            "EditType": "None",
                            "ChildPropertyAlias": {
                              "$type": "Comindware.Platform.Contracts.GlobalAlias, Comindware.Platform.Contracts",
                              "Type": "Undefined"
                            },
                            "OrderPropertyAlias": {
                              "$type": "Comindware.Platform.Contracts.GlobalAlias, Comindware.Platform.Contracts",
                              "Type": "Undefined"
                            },
                            "NumberPropertyAlias": {
                              "$type": "Comindware.Platform.Contracts.GlobalAlias, Comindware.Platform.Contracts",
                              "Type": "Undefined"
                            },
                            "PrecedentPropertyAlias": {
                              "$type": "Comindware.Platform.Contracts.GlobalAlias, Comindware.Platform.Contracts",
                              "Type": "Undefined"
                            },
                            "SortingDirection": "Asc",
                            "PopupFormAlias": {
                              "$type": "Comindware.Platform.Contracts.GlobalAlias, Comindware.Platform.Contracts",
                              "Type": "Undefined"
                            },
                            "AllowEdit": false,
                            "DisplayFormat": "ShowAsPicture",
                            "GlobalAlias": {
                              "$type": "Comindware.Platform.Contracts.GlobalAlias, Comindware.Platform.Contracts",
                              "Type": "FormComponent",
                              "Alias": "Khotelki3_EI"
                            },
                            "AccessType": "Readonly",
                            "Width": 120,
                            "Type": "FieldComponent"
                          },
                          {
                            "$type": "Comindware.Platform.Contracts.FieldComponentModel, Comindware.Platform.Contracts",
                            "Label": {
                              "$type": "Comindware.Platform.Contracts.LabelModel, Comindware.Platform.Contracts",
                              "Hidden": false,
                              "Alignment": "Undefined",
                              "Text": {
                                "$type": "Comindware.Platform.Contracts.LocalizedTextModel, Comindware.Platform.Contracts",
                                "En": "Количество пред. дня",
                                "De": "Количество пред. дня",
                                "Ru": "Количество пред. дня"
                              }
                            },
                            "FieldType": "TableColumn",
                            "Placeholder": {
                              "$type": "Comindware.Platform.Contracts.LocalizedTextModel, Comindware.Platform.Contracts"
                            },
                            "HelpText": {
                              "$type": "Comindware.Platform.Contracts.LocalizedTextModel, Comindware.Platform.Contracts"
                            },
                            "PropertyPath": {
                              "$type": "Comindware.Platform.Contracts.GlobalAlias[], Comindware.Platform.Contracts",
                              "$values": [
                                {
                                  "$type": "Comindware.Platform.Contracts.GlobalAlias, Comindware.Platform.Contracts",
                                  "Type": "Attribute",
                                  "Owner": "Strokiezhednevnoyzayavki",
                                  "Alias": "Kolichestvopreddnya"
                                }
                              ]
                            },
                            "EditorType": "Radio",
                            "CreationType": "None",
                            "RemovalType": "None",
                            "EditType": "None",
                            "ChildPropertyAlias": {
                              "$type": "Comindware.Platform.Contracts.GlobalAlias, Comindware.Platform.Contracts",
                              "Type": "Undefined"
                            },
                            "OrderPropertyAlias": {
                              "$type": "Comindware.Platform.Contracts.GlobalAlias, Comindware.Platform.Contracts",
                              "Type": "Undefined"
                            },
                            "NumberPropertyAlias": {
                              "$type": "Comindware.Platform.Contracts.GlobalAlias, Comindware.Platform.Contracts",
                              "Type": "Undefined"
                            },
                            "PrecedentPropertyAlias": {
                              "$type": "Comindware.Platform.Contracts.GlobalAlias, Comindware.Platform.Contracts",
                              "Type": "Undefined"
                            },
                            "SortingDirection": "Asc",
                            "PopupFormAlias": {
                              "$type": "Comindware.Platform.Contracts.GlobalAlias, Comindware.Platform.Contracts",
                              "Type": "Undefined"
                            },
                            "AllowEdit": false,
                            "DisplayFormat": "ShowAsPicture",
                            "GlobalAlias": {
                              "$type": "Comindware.Platform.Contracts.GlobalAlias, Comindware.Platform.Contracts",
                              "Type": "FormComponent",
                              "Alias": "Khotelki3_Kolichestvopreddnya"
                            },
                            "AccessType": "Readonly",
                            "Width": 120,
                            "Type": "FieldComponent"
                          },
                          {
                            "$type": "Comindware.Platform.Contracts.FieldComponentModel, Comindware.Platform.Contracts",
                            "Label": {
                              "$type": "Comindware.Platform.Contracts.LabelModel, Comindware.Platform.Contracts",
                              "Hidden": false,
                              "Alignment": "Undefined",
                              "Text": {
                                "$type": "Comindware.Platform.Contracts.LocalizedTextModel, Comindware.Platform.Contracts",
                                "En": "Количество факт пред. дня",
                                "De": "Количество факт пред. дня",
                                "Ru": "Количество факт пред. дня"
                              }
                            },
                            "FieldType": "TableColumn",
                            "Placeholder": {
                              "$type": "Comindware.Platform.Contracts.LocalizedTextModel, Comindware.Platform.Contracts"
                            },
                            "HelpText": {
                              "$type": "Comindware.Platform.Contracts.LocalizedTextModel, Comindware.Platform.Contracts"
                            },
                            "PropertyPath": {
                              "$type": "Comindware.Platform.Contracts.GlobalAlias[], Comindware.Platform.Contracts",
                              "$values": [
                                {
                                  "$type": "Comindware.Platform.Contracts.GlobalAlias, Comindware.Platform.Contracts",
                                  "Type": "Attribute",
                                  "Owner": "Strokiezhednevnoyzayavki",
                                  "Alias": "Kolichestvofaktpreddnya"
                                }
                              ]
                            },
                            "EditorType": "Radio",
                            "CreationType": "None",
                            "RemovalType": "None",
                            "EditType": "None",
                            "ChildPropertyAlias": {
                              "$type": "Comindware.Platform.Contracts.GlobalAlias, Comindware.Platform.Contracts",
                              "Type": "Undefined"
                            },
                            "OrderPropertyAlias": {
                              "$type": "Comindware.Platform.Contracts.GlobalAlias, Comindware.Platform.Contracts",
                              "Type": "Undefined"
                            },
                            "NumberPropertyAlias": {
                              "$type": "Comindware.Platform.Contracts.GlobalAlias, Comindware.Platform.Contracts",
                              "Type": "Undefined"
                            },
                            "PrecedentPropertyAlias": {
                              "$type": "Comindware.Platform.Contracts.GlobalAlias, Comindware.Platform.Contracts",
                              "Type": "Undefined"
                            },
                            "SortingDirection": "Asc",
                            "PopupFormAlias": {
                              "$type": "Comindware.Platform.Contracts.GlobalAlias, Comindware.Platform.Contracts",
                              "Type": "Undefined"
                            },
                            "AllowEdit": false,
                            "DisplayFormat": "ShowAsPicture",
                            "GlobalAlias": {
                              "$type": "Comindware.Platform.Contracts.GlobalAlias, Comindware.Platform.Contracts",
                              "Type": "FormComponent",
                              "Alias": "Khotelki3_Kolichestvofaktpreddnya"
                            },
                            "AccessType": "Readonly",
                            "Width": 120,
                            "Type": "FieldComponent"
                          },
                          {
                            "$type": "Comindware.Platform.Contracts.FieldComponentModel, Comindware.Platform.Contracts",
                            "Label": {
                              "$type": "Comindware.Platform.Contracts.LabelModel, Comindware.Platform.Contracts",
                              "Hidden": false,
                              "Alignment": "Undefined",
                              "Text": {
                                "$type": "Comindware.Platform.Contracts.LocalizedTextModel, Comindware.Platform.Contracts",
                                "En": "Количество в проекте",
                                "De": "Количество в проекте",
                                "Ru": "Количество в проекте"
                              }
                            },
                            "FieldType": "TableColumn",
                            "Placeholder": {
                              "$type": "Comindware.Platform.Contracts.LocalizedTextModel, Comindware.Platform.Contracts"
                            },
                            "HelpText": {
                              "$type": "Comindware.Platform.Contracts.LocalizedTextModel, Comindware.Platform.Contracts"
                            },
                            "PropertyPath": {
                              "$type": "Comindware.Platform.Contracts.GlobalAlias[], Comindware.Platform.Contracts",
                              "$values": [
                                {
                                  "$type": "Comindware.Platform.Contracts.GlobalAlias, Comindware.Platform.Contracts",
                                  "Type": "Attribute",
                                  "Owner": "Strokiezhednevnoyzayavki",
                                  "Alias": "Kolichestvovproekte"
                                }
                              ]
                            },
                            "EditorType": "Radio",
                            "CreationType": "None",
                            "RemovalType": "None",
                            "EditType": "None",
                            "ChildPropertyAlias": {
                              "$type": "Comindware.Platform.Contracts.GlobalAlias, Comindware.Platform.Contracts",
                              "Type": "Undefined"
                            },
                            "OrderPropertyAlias": {
                              "$type": "Comindware.Platform.Contracts.GlobalAlias, Comindware.Platform.Contracts",
                              "Type": "Undefined"
                            },
                            "NumberPropertyAlias": {
                              "$type": "Comindware.Platform.Contracts.GlobalAlias, Comindware.Platform.Contracts",
                              "Type": "Undefined"
                            },
                            "PrecedentPropertyAlias": {
                              "$type": "Comindware.Platform.Contracts.GlobalAlias, Comindware.Platform.Contracts",
                              "Type": "Undefined"
                            },
                            "SortingDirection": "Asc",
                            "PopupFormAlias": {
                              "$type": "Comindware.Platform.Contracts.GlobalAlias, Comindware.Platform.Contracts",
                              "Type": "Undefined"
                            },
                            "AllowEdit": false,
                            "DisplayFormat": "ShowAsPicture",
                            "GlobalAlias": {
                              "$type": "Comindware.Platform.Contracts.GlobalAlias, Comindware.Platform.Contracts",
                              "Type": "FormComponent",
                              "Alias": "Khotelki3_Kolichestvovproekte"
                            },
                            "AccessType": "Readonly",
                            "Width": 120,
                            "Type": "FieldComponent"
                          },
                          {
                            "$type": "Comindware.Platform.Contracts.FieldComponentModel, Comindware.Platform.Contracts",
                            "Label": {
                              "$type": "Comindware.Platform.Contracts.LabelModel, Comindware.Platform.Contracts",
                              "Hidden": false,
                              "Alignment": "Undefined",
                              "Text": {
                                "$type": "Comindware.Platform.Contracts.LocalizedTextModel, Comindware.Platform.Contracts",
                                "En": "Время начала",
                                "De": "Время начала",
                                "Ru": "Время начала"
                              }
                            },
                            "FieldType": "TableColumn",
                            "Placeholder": {
                              "$type": "Comindware.Platform.Contracts.LocalizedTextModel, Comindware.Platform.Contracts"
                            },
                            "HelpText": {
                              "$type": "Comindware.Platform.Contracts.LocalizedTextModel, Comindware.Platform.Contracts"
                            },
                            "PropertyPath": {
                              "$type": "Comindware.Platform.Contracts.GlobalAlias[], Comindware.Platform.Contracts",
                              "$values": [
                                {
                                  "$type": "Comindware.Platform.Contracts.GlobalAlias, Comindware.Platform.Contracts",
                                  "Type": "Attribute",
                                  "Owner": "Strokiezhednevnoyzayavki",
                                  "Alias": "Vremyanachala"
                                }
                              ]
                            },
                            "EditorType": "Radio",
                            "CreationType": "None",
                            "RemovalType": "None",
                            "EditType": "None",
                            "ChildPropertyAlias": {
                              "$type": "Comindware.Platform.Contracts.GlobalAlias, Comindware.Platform.Contracts",
                              "Type": "Undefined"
                            },
                            "OrderPropertyAlias": {
                              "$type": "Comindware.Platform.Contracts.GlobalAlias, Comindware.Platform.Contracts",
                              "Type": "Undefined"
                            },
                            "NumberPropertyAlias": {
                              "$type": "Comindware.Platform.Contracts.GlobalAlias, Comindware.Platform.Contracts",
                              "Type": "Undefined"
                            },
                            "PrecedentPropertyAlias": {
                              "$type": "Comindware.Platform.Contracts.GlobalAlias, Comindware.Platform.Contracts",
                              "Type": "Undefined"
                            },
                            "SortingDirection": "Asc",
                            "PopupFormAlias": {
                              "$type": "Comindware.Platform.Contracts.GlobalAlias, Comindware.Platform.Contracts",
                              "Type": "Undefined"
                            },
                            "AllowEdit": false,
                            "DisplayFormat": "ShowAsPicture",
                            "GlobalAlias": {
                              "$type": "Comindware.Platform.Contracts.GlobalAlias, Comindware.Platform.Contracts",
                              "Type": "FormComponent",
                              "Alias": "Khotelki3_Vremyanachala"
                            },
                            "AccessType": "Editable",
                            "Width": 120,
                            "Type": "FieldComponent"
                          },
                          {
                            "$type": "Comindware.Platform.Contracts.FieldComponentModel, Comindware.Platform.Contracts",
                            "Label": {
                              "$type": "Comindware.Platform.Contracts.LabelModel, Comindware.Platform.Contracts",
                              "Hidden": false,
                              "Alignment": "Undefined",
                              "Text": {
                                "$type": "Comindware.Platform.Contracts.LocalizedTextModel, Comindware.Platform.Contracts",
                                "En": "Время окончания",
                                "De": "Время окончания",
                                "Ru": "Время окончания"
                              }
                            },
                            "FieldType": "TableColumn",
                            "Placeholder": {
                              "$type": "Comindware.Platform.Contracts.LocalizedTextModel, Comindware.Platform.Contracts"
                            },
                            "HelpText": {
                              "$type": "Comindware.Platform.Contracts.LocalizedTextModel, Comindware.Platform.Contracts"
                            },
                            "PropertyPath": {
                              "$type": "Comindware.Platform.Contracts.GlobalAlias[], Comindware.Platform.Contracts",
                              "$values": [
                                {
                                  "$type": "Comindware.Platform.Contracts.GlobalAlias, Comindware.Platform.Contracts",
                                  "Type": "Attribute",
                                  "Owner": "Strokiezhednevnoyzayavki",
                                  "Alias": "Vremyaokonchaniya"
                                }
                              ]
                            },
                            "EditorType": "Radio",
                            "CreationType": "None",
                            "RemovalType": "None",
                            "EditType": "None",
                            "ChildPropertyAlias": {
                              "$type": "Comindware.Platform.Contracts.GlobalAlias, Comindware.Platform.Contracts",
                              "Type": "Undefined"
                            },
                            "OrderPropertyAlias": {
                              "$type": "Comindware.Platform.Contracts.GlobalAlias, Comindware.Platform.Contracts",
                              "Type": "Undefined"
                            },
                            "NumberPropertyAlias": {
                              "$type": "Comindware.Platform.Contracts.GlobalAlias, Comindware.Platform.Contracts",
                              "Type": "Undefined"
                            },
                            "PrecedentPropertyAlias": {
                              "$type": "Comindware.Platform.Contracts.GlobalAlias, Comindware.Platform.Contracts",
                              "Type": "Undefined"
                            },
                            "SortingDirection": "Asc",
                            "PopupFormAlias": {
                              "$type": "Comindware.Platform.Contracts.GlobalAlias, Comindware.Platform.Contracts",
                              "Type": "Undefined"
                            },
                            "AllowEdit": false,
                            "DisplayFormat": "ShowAsPicture",
                            "GlobalAlias": {
                              "$type": "Comindware.Platform.Contracts.GlobalAlias, Comindware.Platform.Contracts",
                              "Type": "FormComponent",
                              "Alias": "Khotelki3_Vremyaokonchaniya"
                            },
                            "AccessType": "Editable",
                            "Width": 120,
                            "Type": "FieldComponent"
                          },
                          {
                            "$type": "Comindware.Platform.Contracts.FieldComponentModel, Comindware.Platform.Contracts",
                            "Label": {
                              "$type": "Comindware.Platform.Contracts.LabelModel, Comindware.Platform.Contracts",
                              "Hidden": false,
                              "Alignment": "Undefined",
                              "Text": {
                                "$type": "Comindware.Platform.Contracts.LocalizedTextModel, Comindware.Platform.Contracts",
                                "En": "Комментарий",
                                "De": "Комментарий",
                                "Ru": "Комментарий"
                              }
                            },
                            "FieldType": "TableColumn",
                            "Placeholder": {
                              "$type": "Comindware.Platform.Contracts.LocalizedTextModel, Comindware.Platform.Contracts"
                            },
                            "HelpText": {
                              "$type": "Comindware.Platform.Contracts.LocalizedTextModel, Comindware.Platform.Contracts"
                            },
                            "PropertyPath": {
                              "$type": "Comindware.Platform.Contracts.GlobalAlias[], Comindware.Platform.Contracts",
                              "$values": [
                                {
                                  "$type": "Comindware.Platform.Contracts.GlobalAlias, Comindware.Platform.Contracts",
                                  "Type": "Attribute",
                                  "Owner": "Strokiezhednevnoyzayavki",
                                  "Alias": "Kommentariy"
                                }
                              ]
                            },
                            "EditorType": "Radio",
                            "CreationType": "None",
                            "RemovalType": "None",
                            "EditType": "None",
                            "ChildPropertyAlias": {
                              "$type": "Comindware.Platform.Contracts.GlobalAlias, Comindware.Platform.Contracts",
                              "Type": "Undefined"
                            },
                            "OrderPropertyAlias": {
                              "$type": "Comindware.Platform.Contracts.GlobalAlias, Comindware.Platform.Contracts",
                              "Type": "Undefined"
                            },
                            "NumberPropertyAlias": {
                              "$type": "Comindware.Platform.Contracts.GlobalAlias, Comindware.Platform.Contracts",
                              "Type": "Undefined"
                            },
                            "PrecedentPropertyAlias": {
                              "$type": "Comindware.Platform.Contracts.GlobalAlias, Comindware.Platform.Contracts",
                              "Type": "Undefined"
                            },
                            "SortingDirection": "Asc",
                            "PopupFormAlias": {
                              "$type": "Comindware.Platform.Contracts.GlobalAlias, Comindware.Platform.Contracts",
                              "Type": "Undefined"
                            },
                            "AllowEdit": false,
                            "DisplayFormat": "ShowAsPicture",
                            "GlobalAlias": {
                              "$type": "Comindware.Platform.Contracts.GlobalAlias, Comindware.Platform.Contracts",
                              "Type": "FormComponent",
                              "Alias": "Khotelki3_Kommentariy"
                            },
                            "AccessType": "Editable",
                            "Width": 120,
                            "Type": "FieldComponent"
                          }
                        ]
                      },
                      "ChildPropertyAlias": {
                        "$type": "Comindware.Platform.Contracts.GlobalAlias, Comindware.Platform.Contracts",
                        "Type": "Undefined"
                      },
                      "OrderPropertyAlias": {
                        "$type": "Comindware.Platform.Contracts.GlobalAlias, Comindware.Platform.Contracts",
                        "Type": "Undefined"
                      },
                      "NumberPropertyAlias": {
                        "$type": "Comindware.Platform.Contracts.GlobalAlias, Comindware.Platform.Contracts",
                        "Type": "Undefined"
                      },
                      "PrecedentPropertyAlias": {
                        "$type": "Comindware.Platform.Contracts.GlobalAlias, Comindware.Platform.Contracts",
                        "Type": "Undefined"
                      },
                      "SortingDirection": "Asc",
                      "ShowArchiveRecords": false,
                      "PopupFormAlias": {
                        "$type": "Comindware.Platform.Contracts.GlobalAlias, Comindware.Platform.Contracts",
                        "Type": "Undefined"
                      },
                      "DisplayFormat": "ShowAsPicture",
                      "GlobalAlias": {
                        "$type": "Comindware.Platform.Contracts.GlobalAlias, Comindware.Platform.Contracts",
                        "Type": "FormComponent",
                        "Alias": "Khotelki3"
                      },
                      "AccessType": "Editable",
                      "Width": 0,
                      "Type": "FieldComponent",
                      "Toolbar": {
                        "$type": "System.Nullable`1[[Comindware.Platform.Contracts.GlobalAlias, Comindware.Platform.Contracts]], mscorlib",
                        "Type": "Toolbar",
                        "Owner": "Strokiezhednevnoyzayavki",
                        "Alias": "toolbar251c6edb42a7408991eb7068fb5a82bc"
                      }
                    }
                  ]
                },
                "GlobalAlias": {
                  "$type": "Comindware.Platform.Contracts.GlobalAlias, Comindware.Platform.Contracts",
                  "Type": "FormComponent",
                  "Alias": "VerticalLayout"
                },
                "AccessType": "Undefined",
                "Width": 0,
                "Type": "VerticalLayout"
              }
            ]
          },
          "GlobalAlias": {
            "$type": "Comindware.Platform.Contracts.GlobalAlias, Comindware.Platform.Contracts",
            "Type": "FormComponent",
            "Alias": "GroupPanelComponent"
          },
          "AccessType": "Editable",
          "Width": 100,
          "Type": "PanelModel",
          "Toolbar": {
            "$type": "System.Nullable`1[[Comindware.Platform.Contracts.GlobalAlias, Comindware.Platform.Contracts]], mscorlib",
            "Type": "Toolbar",
            "Owner": "Ezhednevnayazayavka",
            "Alias": "toolbar303d62f7b08f4320a86c241921254906"
          }
        }
      ]
    },
    "GlobalAlias": {
      "$type": "Comindware.Platform.Contracts.GlobalAlias, Comindware.Platform.Contracts",
      "Type": "FormComponent",
      "Alias": "default_Root"
    },
    "AccessType": "Undefined",
    "Width": 0,
    "Type": "VerticalLayout"
  },
  "Name": "Ежедневная заявка - Основная форма",
  "Origination": "Undefined"
}