{
  "$type": "Comindware.Platform.Contracts.FormModel, Comindware.Platform.Contracts",
  "GlobalAlias": {
    "$type": "Comindware.Platform.Contracts.GlobalAlias, Comindware.Platform.Contracts",
    "Type": "ProcessForm",
    "Owner": "rabotadispetchera",
    "Alias": "form2865834a4d9e41628a067468dfc0790e"
  },
  "Type": "PublicForm",
  "IsDefault": false,
  "Root": {
    "$type": "Comindware.Platform.Contracts.VerticalLayoutModel, Comindware.Platform.Contracts",
    "GlobalAlias": {
      "$type": "Comindware.Platform.Contracts.GlobalAlias, Comindware.Platform.Contracts",
      "Type": "FormComponent",
      "Alias": "default_Root"
    },
    "AccessType": "Undefined",
    "Width": 0,
    "Type": "VerticalLayout"
  },
  "Origination": "Undefined"
}